pyuptimekuma/__init__.py
pyuptimekuma/const.py
pyuptimekuma/decorator.py
pyuptimekuma/exceptions.py
pyuptimekuma/models.py
pyuptimekuma/uptimekuma.py
pyuptimekuma-0.0.6.dist-info/LICENSE
pyuptimekuma-0.0.6.dist-info/METADATA
pyuptimekuma-0.0.6.dist-info/WHEEL
pyuptimekuma-0.0.6.dist-info/top_level.txt
pyuptimekuma-0.0.6.dist-info/zip-safe
pyuptimekuma-0.0.6.dist-info/RECORD
